{
  "display": {
    "icon": {
      "item": "sfd_comets:crude_mallet"
    },
    "title": "01 Stage 1 - The Beginning",
    "description": "Trigger: Crafting Table. Exit: stabiler Bio/Earth/Soil-Loop mit reproduzierbarem Dirt.",
    "background": "minecraft:textures/block/stripped_oak_log.png",
    "x": 2.0,
    "y": 0.0,
    "frame": "goal",
    "show_toast": true,
    "announce_to_chat": false,
    "hidden": false
  },
  "criteria": {
    "manual_unlock": {
      "trigger": "minecraft:impossible"
    }
  }
}


